mqttwrapper/__init__.py
mqttwrapper/hbmqtt_backend.py
mqttwrapper/paho_backend.py
mqttwrapper/run.py
mqttwrapper-0.2.0.dist-info/licenses/LICENSE
mqttwrapper-0.2.0.dist-info/METADATA
mqttwrapper-0.2.0.dist-info/WHEEL
mqttwrapper-0.2.0.dist-info/top_level.txt
mqttwrapper-0.2.0.dist-info/RECORD
