Metadata-Version: 2.4
Name: mqttwrapper
Version: 0.2.0
Summary: MQTT utility scripts made easy
Home-page: https://github.com/davea/mqttwrapper
Author: Dave Arter
Author-email: pypi@davea.me
License: MIT
Keywords: mqtt
Classifier: Development Status :: 3 - Alpha
Classifier: Intended Audience :: Developers
Classifier: Topic :: Software Development :: Build Tools
Classifier: License :: OSI Approved :: MIT License
Classifier: Programming Language :: Python :: 3
Classifier: Programming Language :: Python :: 3.5
Classifier: Programming Language :: Python :: 3.6
Classifier: Programming Language :: Python :: 3.7
License-File: LICENSE
Requires-Dist: paho-mqtt>=2.0.0
Provides-Extra: hbmqtt
Requires-Dist: hbmqtt; extra == "hbmqtt"
Dynamic: author
Dynamic: author-email
Dynamic: classifier
Dynamic: description
Dynamic: home-page
Dynamic: keywords
Dynamic: license
Dynamic: license-file
Dynamic: provides-extra
Dynamic: requires-dist
Dynamic: summary
